asimpy/__init__.py
asimpy/_adapt.py
asimpy/allof.py
asimpy/barrier.py
asimpy/environment.py
asimpy/event.py
asimpy/firstof.py
asimpy/interrupt.py
asimpy/process.py
asimpy/resource.py
asimpy/simqueue.py
asimpy/timeout.py
asimpy-0.4.1.dist-info/METADATA
asimpy-0.4.1.dist-info/WHEEL
asimpy-0.4.1.dist-info/licenses/LICENSE.md
asimpy-0.4.1.dist-info/RECORD
