Metadata-Version: 2.4
Name: asimpy
Version: 0.4.1
Summary: A simple discrete event simulator using async/await
Author-email: Greg Wilson <gvwilson@third-bit.com>
Maintainer-email: Greg Wilson <gvwilson@third-bit.com>
License-File: LICENSE.md
Keywords: discrete event simulation,open source
Classifier: License :: OSI Approved :: MIT License
Classifier: Operating System :: OS Independent
Classifier: Programming Language :: Python :: 3
Requires-Python: >=3.12
Provides-Extra: dev
Requires-Dist: build>=1.4.0; extra == 'dev'
Requires-Dist: markdown-include>=0.8.1; extra == 'dev'
Requires-Dist: mkdocs-awesome-pages-plugin>=2.10.1; extra == 'dev'
Requires-Dist: mkdocs-material>=9.7.1; extra == 'dev'
Requires-Dist: mkdocs>=1.6.1; extra == 'dev'
Requires-Dist: mkdocstrings[python]>=1.0.0; extra == 'dev'
Requires-Dist: ruff>=0.14.10; extra == 'dev'
Requires-Dist: taskipy>=1.14.1; extra == 'dev'
Requires-Dist: twine>=6.2.0; extra == 'dev'
Requires-Dist: ty>=0.0.11; extra == 'dev'
